crypto_analysis/__init__.py
crypto_analysis/app.py
crypto_analysis/exception.py
crypto_analysis/model.py
crypto_analysis/utils.py
HACryptoAnalysis-0.0.2.dist-info/LICENSE
HACryptoAnalysis-0.0.2.dist-info/METADATA
HACryptoAnalysis-0.0.2.dist-info/WHEEL
HACryptoAnalysis-0.0.2.dist-info/entry_points.txt
HACryptoAnalysis-0.0.2.dist-info/top_level.txt
HACryptoAnalysis-0.0.2.dist-info/RECORD
