Metadata-Version: 2.1
Name: HACryptoAnalysis
Version: 0.0.2
Summary: A web app to analyse cryptocurrency prices and use technical indicators
Home-page: https://github.com/azizelkadi/Proyecto-python
Author: Hector Gonzalez - Abdelaziz el Kadi
Author-email: azizelkadi24@gmail.com
Classifier: Programming Language :: Python :: 3
Classifier: License :: OSI Approved :: MIT License
Classifier: Operating System :: OS Independent
Requires-Python: >=3.10
License-File: LICENSE
